[
  {
    "line": 6,
    "elements": [
      {
        "line": 12,
        "name": "# Define os passos que são sempre executados nos cenários",
        "description": "",
        "type": "background",
        "keyword": "Contexto",
        "steps": [
          {
            "result": {
              "duration": 28877499405,
              "status": "passed"
            },
            "line": 13,
            "name": "que desejo adicionar uma conta",
            "match": {
              "location": "InserirContasSteps.queDesejoAdicionarUmaConta()"
            },
            "keyword": "Dado "
          }
        ]
      },
      {
        "start_timestamp": "2020-05-23T16:03:16.732Z",
        "line": 21,
        "name": "Deve validar regras cadastro contas",
        "description": "",
        "id": "cadastro-de-contas;deve-validar-regras-cadastro-contas;;2",
        "after": [
          {
            "result": {
              "duration": 331400350,
              "status": "passed"
            },
            "match": {
              "location": "InserirContasSteps.sreenshot(Scenario)"
            }
          },
          {
            "result": {
              "duration": 3885758754,
              "status": "passed"
            },
            "match": {
              "location": "InserirContasSteps.fecharBrowser()"
            }
          }
        ],
        "type": "scenario",
        "keyword": "Esquema do Cenário",
        "steps": [
          {
            "result": {
              "duration": 1338749361,
              "status": "passed"
            },
            "line": 16,
            "name": "adiciono a conta \"Conta de Teste\"",
            "match": {
              "arguments": [
                {
                  "val": "Conta de Teste",
                  "offset": 18
                }
              ],
              "location": "InserirContasSteps.adicionoAConta(String)"
            },
            "keyword": "Quando "
          },
          {
            "result": {
              "duration": 79015529,
              "status": "passed"
            },
            "line": 17,
            "name": "recebo a mensagem \"Conta adicionada com sucesso!\"",
            "match": {
              "arguments": [
                {
                  "val": "Conta adicionada com sucesso!",
                  "offset": 19
                }
              ],
              "location": "InserirContasSteps.receboAMensagem(String)"
            },
            "keyword": "Então "
          }
        ],
        "tags": [
          {
            "name": "@funcionais"
          }
        ]
      },
      {
        "line": 12,
        "name": "# Define os passos que são sempre executados nos cenários",
        "description": "",
        "type": "background",
        "keyword": "Contexto",
        "steps": [
          {
            "result": {
              "duration": 30212682507,
              "status": "passed"
            },
            "line": 13,
            "name": "que desejo adicionar uma conta",
            "match": {
              "location": "InserirContasSteps.queDesejoAdicionarUmaConta()"
            },
            "keyword": "Dado "
          }
        ]
      },
      {
        "start_timestamp": "2020-05-23T16:03:51.346Z",
        "line": 22,
        "name": "Deve validar regras cadastro contas",
        "description": "",
        "id": "cadastro-de-contas;deve-validar-regras-cadastro-contas;;3",
        "after": [
          {
            "result": {
              "duration": 180245825,
              "status": "passed"
            },
            "match": {
              "location": "InserirContasSteps.sreenshot(Scenario)"
            }
          },
          {
            "result": {
              "duration": 4380258697,
              "status": "passed"
            },
            "match": {
              "location": "InserirContasSteps.fecharBrowser()"
            }
          }
        ],
        "type": "scenario",
        "keyword": "Esquema do Cenário",
        "steps": [
          {
            "result": {
              "duration": 1420678749,
              "status": "passed"
            },
            "line": 16,
            "name": "adiciono a conta \"\"",
            "match": {
              "arguments": [
                {
                  "val": "",
                  "offset": 18
                }
              ],
              "location": "InserirContasSteps.adicionoAConta(String)"
            },
            "keyword": "Quando "
          },
          {
            "result": {
              "duration": 192530748,
              "status": "passed"
            },
            "line": 17,
            "name": "recebo a mensagem \"Informe o nome da conta\"",
            "match": {
              "arguments": [
                {
                  "val": "Informe o nome da conta",
                  "offset": 19
                }
              ],
              "location": "InserirContasSteps.receboAMensagem(String)"
            },
            "keyword": "Então "
          }
        ],
        "tags": [
          {
            "name": "@funcionais"
          }
        ]
      },
      {
        "line": 12,
        "name": "# Define os passos que são sempre executados nos cenários",
        "description": "",
        "type": "background",
        "keyword": "Contexto",
        "steps": [
          {
            "result": {
              "duration": 17821948834,
              "status": "passed"
            },
            "line": 13,
            "name": "que desejo adicionar uma conta",
            "match": {
              "location": "InserirContasSteps.queDesejoAdicionarUmaConta()"
            },
            "keyword": "Dado "
          }
        ]
      },
      {
        "start_timestamp": "2020-05-23T16:04:27.748Z",
        "line": 23,
        "name": "Deve validar regras cadastro contas",
        "description": "",
        "id": "cadastro-de-contas;deve-validar-regras-cadastro-contas;;4",
        "after": [
          {
            "result": {
              "duration": 127567181,
              "status": "passed"
            },
            "match": {
              "location": "InserirContasSteps.sreenshot(Scenario)"
            }
          },
          {
            "result": {
              "duration": 2144656364,
              "status": "passed"
            },
            "match": {
              "location": "InserirContasSteps.fecharBrowser()"
            }
          }
        ],
        "type": "scenario",
        "keyword": "Esquema do Cenário",
        "steps": [
          {
            "result": {
              "duration": 767420746,
              "status": "passed"
            },
            "line": 16,
            "name": "adiciono a conta \"Conta mesmo nome\"",
            "match": {
              "arguments": [
                {
                  "val": "Conta mesmo nome",
                  "offset": 18
                }
              ],
              "location": "InserirContasSteps.adicionoAConta(String)"
            },
            "keyword": "Quando "
          },
          {
            "result": {
              "duration": 68755096,
              "status": "passed"
            },
            "line": 17,
            "name": "recebo a mensagem \"Já existe uma conta com esse nome!\"",
            "match": {
              "arguments": [
                {
                  "val": "Já existe uma conta com esse nome!",
                  "offset": 19
                }
              ],
              "location": "InserirContasSteps.receboAMensagem(String)"
            },
            "keyword": "Então "
          }
        ],
        "tags": [
          {
            "name": "@funcionais"
          }
        ]
      }
    ],
    "name": "Cadastro de contas",
    "description": "\tComo um usuário \n\tGostaria de cadastrar contas\n\tPara que eu possa distribuir meu dinheiro de uma forma mais organizada",
    "id": "cadastro-de-contas",
    "keyword": "Funcionalidade",
    "uri": "file:src/test/resources/features/inserir_conta.feature",
    "tags": [
      {
        "name": "@funcionais",
        "type": "Tag",
        "location": {
          "line": 5,
          "column": 1
        }
      }
    ]
  }
]